{
    "version": "0.27.0",
    "architecture": {
        "64bit": {
            "url": "http://github.com/smallstep/certificates/releases/download/v0.27.0/step-ca_windows_0.27.0_amd64.zip",
            "bin": [
                "step-ca.exe"
            ],
            "hash": "f8aab7955c13975a2a42547ce7c6284e862210f1319dc1aaabf7da994cda244a"
        }
    },
    "homepage": "https://smallstep.com/docs/step-ca",
    "license": "Apache-2.0",
    "description": "A private certificate authority (X.509 \u0026 SSH) \u0026 ACME server for secure automated certificate management, so you can use TLS everywhere \u0026 SSO for SSH."
}